peachbase-0.4.2.dist-info/RECORD
peachbase-0.4.2.dist-info/WHEEL
peachbase-0.4.2.dist-info/top_level.txt
peachbase-0.4.2.dist-info/METADATA
peachbase-0.4.2.dist-info/licenses/LICENSE
peachbase/query.py
peachbase/_version.py
peachbase/database.py
peachbase/__init__.py
peachbase/_simd.cpython-313-darwin.so
peachbase/_bm25.cpython-313-darwin.so
peachbase/collection.py
peachbase/utils/__init__.py
peachbase/utils/s3.py
peachbase/storage/__init__.py
peachbase/storage/format.py
peachbase/storage/reader.py
peachbase/storage/writer.py
peachbase/search/bm25.py
peachbase/search/semantic.py
peachbase/search/hybrid.py
peachbase/search/__init__.py
peachbase/search/filters.py
peachbase/text/__init__.py
peachbase/text/tokenizer.py
