Metadata-Version: 2.4
Name: peachbase
Version: 0.4.2
Summary: Lightweight vector database optimized for AWS Lambda with lexical, semantic, and hybrid search
Author-email: Philipp <philipp@peachstone.ai>
License: MIT
Project-URL: Homepage, https://github.com/PeachstoneAI/PeachBase
Project-URL: Documentation, https://github.com/PeachstoneAI/PeachBase#readme
Project-URL: Repository, https://github.com/PeachstoneAI/PeachBase
Project-URL: Issues, https://github.com/PeachstoneAI/PeachBase/issues
Keywords: vector-database,search,embeddings,lambda,bm25,semantic-search,hybrid-search
Classifier: Development Status :: 4 - Beta
Classifier: Intended Audience :: Developers
Classifier: License :: OSI Approved :: MIT License
Classifier: Programming Language :: Python :: 3.13
Classifier: Programming Language :: Python :: 3.14
Classifier: Programming Language :: C
Classifier: Topic :: Database
Classifier: Topic :: Scientific/Engineering :: Artificial Intelligence
Classifier: Topic :: Software Development :: Libraries :: Python Modules
Requires-Python: >=3.13
License-File: LICENSE
Requires-Dist: boto3>=1.34.0
Provides-Extra: dev
Requires-Dist: pytest>=7.0; extra == "dev"
Requires-Dist: pytest-cov>=4.0; extra == "dev"
Requires-Dist: pytest-benchmark>=4.0; extra == "dev"
Requires-Dist: ruff>=0.3.0; extra == "dev"
Requires-Dist: mypy>=1.8; extra == "dev"
Provides-Extra: test
Requires-Dist: pytest>=7.0; extra == "test"
Requires-Dist: pytest-cov>=4.0; extra == "test"
Dynamic: license-file
